fyCursor/__init__.py
fyCursor/__main__.py
fyCursor/core/__init__.py
fyCursor/core/core.py
fyCursor/core/fields.py
fyCursor-0.1.6.dist-info/LICENSE
fyCursor-0.1.6.dist-info/METADATA
fyCursor-0.1.6.dist-info/WHEEL
fyCursor-0.1.6.dist-info/top_level.txt
fyCursor-0.1.6.dist-info/RECORD
