Metadata-Version: 2.1
Name: fyCursor
Version: 0.1.6
Summary: Simple sqlite3 cursor
Author: felixyeahh
Author-email: <felixyeah@outlook.com>
License: MIT
Keywords: python,sqlite3,database
License-File: LICENSE
